xanity/__init__.py
xanity/__main__.py
xanity/class_obj.py
xanity/common.py
xanity/constants.py
xanity/xanity_data.py
xanity/xanity_develop.py
xanity/xanity_env.py
xanity/xanity_init.py
xanity/xanity_run.py
xanity/skeleton/.gitignore
xanity/skeleton/METADATA.md
xanity/skeleton/README.md
xanity/skeleton/conda_environment.yaml
xanity/skeleton/.xanity/.gitignore
xanity/skeleton/analyses/README.md
xanity/skeleton/analyses/analysis1.py_EXAMPLE
xanity/skeleton/analyses/analysis2.py_EXAMPLE
xanity/skeleton/analyses/analysis3.py_EXAMPLE
xanity/skeleton/data/persistent/README.md
xanity/skeleton/data/persistent/persist_lib/README.md
xanity/skeleton/data/runs/README.md
xanity/skeleton/data/saved/README.md
xanity/skeleton/docs/README.md
xanity/skeleton/experiments/README.md
xanity/skeleton/experiments/experiment1.py_EXAMPLE
xanity/skeleton/experiments/experiment1b.py_EXAMPLE
xanity/skeleton/experiments/experiment2.py_EXAMPLE
xanity/skeleton/experiments/experiment3.py_EXAMPLE
xanity/skeleton/include/README.md
xanity/xanity_self_replication/README.md
xanity/xanity_self_replication/setup.py
xanity/xanity_self_replication/xanity/__init__.py
xanity/xanity_self_replication/xanity/__main__.py
xanity/xanity_self_replication/xanity/class_obj.py
xanity/xanity_self_replication/xanity/common.py
xanity/xanity_self_replication/xanity/constants.py
xanity/xanity_self_replication/xanity/xanity_data.py
xanity/xanity_self_replication/xanity/xanity_develop.py
xanity/xanity_self_replication/xanity/xanity_env.py
xanity/xanity_self_replication/xanity/xanity_init.py
xanity/xanity_self_replication/xanity/xanity_run.py
xanity/xanity_self_replication/xanity/bin/xanity
xanity/xanity_self_replication/xanity/bin/xanity.bash
xanity/xanity_self_replication/xanity/bin/xanity.entry_script
xanity/xanity_self_replication/xanity/skeleton/.gitignore
xanity/xanity_self_replication/xanity/skeleton/METADATA.md
xanity/xanity_self_replication/xanity/skeleton/conda_environment.yaml
xanity-0.3b3.dist-info/LICENSE
xanity-0.3b3.dist-info/METADATA
xanity-0.3b3.dist-info/WHEEL
xanity-0.3b3.dist-info/entry_points.txt
xanity-0.3b3.dist-info/top_level.txt
xanity-0.3b3.dist-info/RECORD
