Metadata-Version: 2.1
Name: xanity
Version: 0.3b3
Summary: Package for managing experiments and analyses
Home-page: http://gitlab.com/bjmuld/xanity/
Author: Barry Muldrey
Author-email: barry@muldrey.net
License: GPLv3
Project-URL: Bug Tracker, https://gitlab.com/bjmuld/xanity/issues
Project-URL: Documentation, https://gitlab.com/bjmuld/xanity
Keywords: scientific experiements analysis data management
Platform: UNKNOWN
Classifier: Development Status :: 3 - Alpha
Classifier: Environment :: Console
Classifier: Intended Audience :: End Users/Desktop
Classifier: Intended Audience :: Developers
Classifier: Intended Audience :: Science/Research
Classifier: Intended Audience :: Education
Classifier: License :: OSI Approved :: GNU Affero General Public License v3
Classifier: Operating System :: MacOS
Classifier: Operating System :: Microsoft :: Windows
Classifier: Operating System :: POSIX
Classifier: Natural Language :: English
Classifier: Programming Language :: Python
Classifier: Topic :: Scientific/Engineering
Classifier: Topic :: Scientific/Engineering :: Visualization
Classifier: Topic :: Utilities
Requires-Python: >=2.7
Requires-Dist: dill
Requires-Dist: pandas
Requires-Dist: pyparsing
Requires-Dist: cloudpickle
Requires-Dist: ipdb
Requires-Dist: numpy
Provides-Extra: dev
Requires-Dist: pytest ; extra == 'dev'
Requires-Dist: tox ; extra == 'dev'
